{
  "title":"Trinity and simplicity (4)",
  "date":"2022-11-03T23:52:19.000000Z",
  "author":null,
  "id":"http://thomism.wordpress.com/?p=26151",
  "link":"https://thomism.wordpress.com/2022/11/03/trinity-and-simplicity-4/",
  "content":"<p>God, pure act, transcends all limitation of perfection.</p>\n<p>The real distinction of absolute attributes is a limitation. So no real distinction of these is allowed in God. The distinction of wisdom from mercy from omnipotence arises from the limitation of our intellect.</p>\n<p>The real distinction of relative attributes from each other is not a limitation.</p>\n<p>The distinction of absolute from relative attributes is a limitation.</p>\n"
}