{
  "title":"Chinese COVID-19 Restrictions Now Affecting Shipments of iPhones 14 Pro and Pro Max",
  "date":"2022-11-07T16:46:18.000000Z",
  "author":"John Gruber",
  "id":"tag:daringfireball.net,2022:/linked//6.39465",
  "link":"https://www.apple.com/newsroom/2022/11/update-on-supply-of-iphone-14-pro-and-iphone-14-pro-max/",
  "content":"\n<p>Apple:</p>\n\n<blockquote>\n  <p>COVID-19 restrictions have temporarily impacted the primary iPhone 14 Pro and iPhone 14 Pro Max assembly facility located in Zhengzhou, China. The facility is currently operating at significantly reduced capacity. As we have done throughout the COVID-19 pandemic, we are prioritizing the health and safety of the workers in our supply chain.</p>\n\n<p>We continue to see strong demand for iPhone 14 Pro and iPhone 14 Pro Max models. However, we now expect lower iPhone 14 Pro and iPhone 14 Pro Max shipments than we previously anticipated and customers will experience longer wait times to receive their new products.</p>\n</blockquote>\n\n<p>The writing <a href=\"https://www.taiwannews.com.tw/en/news/4705481\">has been on the wall with this outbreak</a>.</p>\n\n<div>\n<a title=\"Permanent link to ‘Chinese COVID-19 Restrictions Now Affecting Shipments of iPhones 14 Pro and Pro Max’\" href=\"https://daringfireball.net/linked/2022/11/07/iphone-14-covid\"> ★ </a>\n</div>\n\n\t"
}