{
  "metadata":
{
  "title":"The Ruby on Rails Podcast",
  "fetch-url":"http://feeds.5by5.tv/rubyonrails",
  "link":"https://www.therubyonrailspodcast.com",
  "description":"The Ruby on Rails Podcast, a weekly conversation about Ruby on Rails, open source software, and the programming profession. Co-hosted by Brittany Martin, Brian Mariani, Jemma Issroff and Nick Schwaderer. Produced by Mirror Placement. Edited by Peachtree Sound.\n"
},
  "items":
  [
    {
      "title":"Episode 444: Artificial Intelligence on Rails with Kevin Su",
      "path":"2022-11-16T13:00:00.000000Z-55de9cf31eafe52a2e32efde4493b1f4c485d0a9afd72ab3b0a75a6f4afda9ff.json"
    },
    {
      "title":"Episode 443: Your Network Is Your Net Worth with Roman Turner",
      "path":"2022-11-09T13:00:00.000000Z-2b171762f617fd838079708220eccff1e97c1412c189d8b11643eaeda5631bde.json"
    },
    {
      "title":"Episode 442: Sierra Rails (The Apprenticeship Pattern) with Dave Paola",
      "path":"2022-11-02T12:00:00.000000Z-3880d41e356e73796744ce45de68baa2054ef821aaf285c38f0dbf7f84a07604.json"
    },
    {
      "title":"Episode 441: The Pursuit of Mentorship with Meghan Gutshall",
      "path":"2022-10-26T12:00:00.000000Z-23de2994350fb80d52a066cb70a00b5794c374ea6bf72d5b987ec3cee326e123.json"
    },
    {
      "title":"Episode 440: World Traveler and Ruby 3.2 Preview (Brittany + Jemma)",
      "path":"2022-10-19T12:00:00.000000Z-f7c5a1d106725fb27b4b3d9232b89ef5de196dc422ea1e16c210ed1972fb602c.json"
    }
  ]
}